utils/__init__.py
utils/converter_utils.py
utils/excel_template_constants.py
ExcelToSBOL-1.0.0a0.dist-info/METADATA
ExcelToSBOL-1.0.0a0.dist-info/WHEEL
ExcelToSBOL-1.0.0a0.dist-info/top_level.txt
ExcelToSBOL-1.0.0a0.dist-info/RECORD
